uri_template/__init__.py
uri_template/charset.py
uri_template/expansions.py
uri_template/py.typed
uri_template/uritemplate.py
uri_template/variable.py
uri_template-1.2.0.dist-info/LICENSE
uri_template-1.2.0.dist-info/METADATA
uri_template-1.2.0.dist-info/WHEEL
uri_template-1.2.0.dist-info/top_level.txt
uri_template-1.2.0.dist-info/RECORD
