Metadata-Version: 2.1
Name: uri_template
Version: 1.2.0
Summary: RFC 6570 URI Template Processor
Home-page: https://github.com/plinss/uri_template/
Author: Peter Linss
Author-email: pypi@linss.com
License: UNKNOWN
Platform: UNKNOWN
Classifier: Programming Language :: Python :: 3
Classifier: License :: OSI Approved :: MIT License
Classifier: Operating System :: OS Independent
Requires-Python: >=3.6
Provides-Extra: dev
License-File: LICENSE
